odoo/addons/account_tax_one_vat/README.rst
odoo/addons/account_tax_one_vat/__init__.py
odoo/addons/account_tax_one_vat/__manifest__.py
odoo/addons/account_tax_one_vat/i18n/account_tax_one_vat.pot
odoo/addons/account_tax_one_vat/i18n/es.po
odoo/addons/account_tax_one_vat/i18n/fr_BE.po
odoo/addons/account_tax_one_vat/i18n/it.po
odoo/addons/account_tax_one_vat/models/__init__.py
odoo/addons/account_tax_one_vat/models/account_move.py
odoo/addons/account_tax_one_vat/models/account_move_line.py
odoo/addons/account_tax_one_vat/models/account_tax.py
odoo/addons/account_tax_one_vat/models/account_tax_template.py
odoo/addons/account_tax_one_vat/models/one_vat_mixin.py
odoo/addons/account_tax_one_vat/models/product_template.py
odoo/addons/account_tax_one_vat/models/res_company.py
odoo/addons/account_tax_one_vat/models/res_config_settings.py
odoo/addons/account_tax_one_vat/readme/CONTRIBUTORS.rst
odoo/addons/account_tax_one_vat/readme/DESCRIPTION.rst
odoo/addons/account_tax_one_vat/readme/USAGE.rst
odoo/addons/account_tax_one_vat/static/description/icon.png
odoo/addons/account_tax_one_vat/static/description/index.html
odoo/addons/account_tax_one_vat/tests/__init__.py
odoo/addons/account_tax_one_vat/tests/common.py
odoo/addons/account_tax_one_vat/tests/test_account_tax_one_vat.py
odoo/addons/account_tax_one_vat/views/account_tax_views.xml
odoo/addons/account_tax_one_vat/views/res_config_settings_views.xml
odoo_addon_account_tax_one_vat-16.0.1.0.0.6.dist-info/METADATA
odoo_addon_account_tax_one_vat-16.0.1.0.0.6.dist-info/WHEEL
odoo_addon_account_tax_one_vat-16.0.1.0.0.6.dist-info/top_level.txt
odoo_addon_account_tax_one_vat-16.0.1.0.0.6.dist-info/RECORD
